djangorestframework_registration-0.0.2.dist-info/DESCRIPTION.rst
djangorestframework_registration-0.0.2.dist-info/METADATA
djangorestframework_registration-0.0.2.dist-info/RECORD
djangorestframework_registration-0.0.2.dist-info/WHEEL
djangorestframework_registration-0.0.2.dist-info/metadata.json
djangorestframework_registration-0.0.2.dist-info/top_level.txt
rest_framework_registration/__init__.py
rest_framework_registration/serializers.py
rest_framework_registration/signals.py
rest_framework_registration/urls.py
rest_framework_registration/views.py
rest_framework_registration/__pycache__/__init__.cpython-34.pyc
rest_framework_registration/__pycache__/models.cpython-34.pyc
rest_framework_registration/__pycache__/serializers.cpython-34.pyc
rest_framework_registration/__pycache__/signals.cpython-34.pyc
rest_framework_registration/__pycache__/urls.cpython-34.pyc
rest_framework_registration/__pycache__/views.cpython-34.pyc
